{
    "entityNumberCounter": 16,
    "entities": [
        {
            "hierarchyOrder": 3.0,
            "name": "Empty Entity",
            "uniqueNumber": 10,
            "parent": -1,
            "exposed": true,
            "collapsedChildren": false,
            "components": [
                {
                    "name": "transform",
                    "specifics": "{\"pos\":{\"x\":9.46500015258789,\"y\":0.0,\"z\":7.031000137329102},\"rot\":{\"x\":0.0,\"y\":0.7933533787727356,\"z\":0.0,\"w\":-0.6087614893913269},\"scale\":{\"x\":1.0,\"y\":1.0,\"z\":1.0}}"
                }
            ]
        },
        {
            "hierarchyOrder": 2.0,
            "name": "Tent 02",
            "uniqueNumber": 13,
            "parent": -1,
            "exposed": false,
            "collapsedChildren": false,
            "components": [
                {
                    "name": "transform",
                    "specifics": "{\"pos\":{\"x\":12.75,\"y\":0.0,\"z\":10.75},\"rot\":{\"x\":0.0,\"y\":0.0,\"z\":0.0,\"w\":1.0},\"scale\":{\"x\":1.0,\"y\":1.0,\"z\":1.0}}"
                },
                {
                    "name": "GLTFShape",
                    "specifics": "{\"assetID\":\"ea911723-12bb-4476-a282-81edd7d56afc\"}"
                }
            ]
        },
        {
            "hierarchyOrder": 0.0,
            "name": "Floor Base Grass 01",
            "uniqueNumber": 14,
            "parent": -1,
            "exposed": false,
            "collapsedChildren": false,
            "components": [
                {
                    "name": "transform",
                    "specifics": "{\"pos\":{\"x\":8.0,\"y\":0.0,\"z\":8.0},\"rot\":{\"x\":0.0,\"y\":0.0,\"z\":0.0,\"w\":1.0},\"scale\":{\"x\":1.0,\"y\":1.0,\"z\":1.0}}"
                },
                {
                    "name": "GLTFShape",
                    "specifics": "{\"assetID\":\"f1a5a6ce-80b7-49ab-9a09-972a39b7882f\"}"
                }
            ]
        },
        {
            "hierarchyOrder": 1.0,
            "name": "Fence Stone Tall Small 01",
            "uniqueNumber": 15,
            "parent": -1,
            "exposed": false,
            "collapsedChildren": false,
            "components": [
                {
                    "name": "transform",
                    "specifics": "{\"pos\":{\"x\":16.0,\"y\":0.0,\"z\":9.0},\"rot\":{\"x\":0.0,\"y\":0.0,\"z\":0.0,\"w\":1.0},\"scale\":{\"x\":1.0,\"y\":1.0,\"z\":8.75}}"
                },
                {
                    "name": "GLTFShape",
                    "specifics": "{\"assetID\":\"12f7ea58-b3e1-47cc-9ba6-95b9fe72a10b\"}"
                }
            ]
        }
    ]
}
